ghana_nlp/__init__.py
ghana_nlp/api.py
ghana_nlp-0.1.4.dist-info/LICENSE
ghana_nlp-0.1.4.dist-info/METADATA
ghana_nlp-0.1.4.dist-info/WHEEL
ghana_nlp-0.1.4.dist-info/top_level.txt
ghana_nlp-0.1.4.dist-info/RECORD
