Metadata-Version: 2.1
Name: ghana-nlp
Version: 0.1.4
Summary: A Python library for interacting with the GhanaNLP API
Home-page: https://pnlarbi.vercel.app/
Author: Prince Larbi
Author-email: phiddyconcept@gmail.com
Project-URL: Source, https://github.com/PhidLarkson/Ghana-NLP-Python-Library
Project-URL: Documentation, https://pkwolffe.hashnode.dev/ghana-nlp-python-library
Classifier: Programming Language :: Python :: 3
Classifier: License :: OSI Approved :: MIT License
Classifier: Operating System :: OS Independent
Requires-Python: >=3.6
License-File: LICENSE
Requires-Dist: requests
